setup.py
django_email_template.egg-info/PKG-INFO
django_email_template.egg-info/SOURCES.txt
django_email_template.egg-info/dependency_links.txt
django_email_template.egg-info/not-zip-safe
django_email_template.egg-info/top_level.txt
email_template/__init__.py
email_template/email.py
email_template/util.py