Metadata-Version: 1.0
Name: django-email-template
Version: 1.0.2
Summary: Send emails based on a Django template
Home-page: UNKNOWN
Author: UNKNOWN
Author-email: UNKNOWN
License: UNKNOWN
Platform: UNKNOWN
